bustard/__init__.py
bustard/app.py
bustard/constants.py
bustard/exceptions.py
bustard/http.py
bustard/orm.py
bustard/router.py
bustard/servers.py
bustard/sessions.py
bustard/template.py
bustard/testing.py
bustard/utils.py
bustard/views.py
bustard/wsgi_server.py
bustard-0.1.6.dist-info/DESCRIPTION.rst
bustard-0.1.6.dist-info/METADATA
bustard-0.1.6.dist-info/metadata.json
bustard-0.1.6.dist-info/RECORD
bustard-0.1.6.dist-info/top_level.txt
bustard-0.1.6.dist-info/WHEEL
